audiobook_player/__init__.py
audiobook_player/__main__.py
audiobook_player/audioplayer.py
audiobook_player/cli.py
audiobook_player-0.0.1.dist-info/licenses/LICENSE
audiobook_player-0.0.1.dist-info/METADATA
audiobook_player-0.0.1.dist-info/WHEEL
audiobook_player-0.0.1.dist-info/entry_points.txt
audiobook_player-0.0.1.dist-info/top_level.txt
audiobook_player-0.0.1.dist-info/RECORD
