Metadata-Version: 2.4
Name: audiobook-player
Version: 0.0.1
Summary: Simple audiobook player
Author: Sukhbinder Singh
License: Apache-2.0
Project-URL: Homepage, https://github.com/sukhbinder/audiobook-player
Project-URL: Changelog, https://github.com/sukhbinder/audiobook-player/releases
Project-URL: Issues, https://github.com/sukhbinder/audiobook-player/issues
Project-URL: CI, https://github.com/sukhbinder/audiobook-player/actions
Requires-Python: >=3.8
License-File: LICENSE
Requires-Dist: afplay-win; platform_system == "Windows"
Requires-Dist: mutagen
Provides-Extra: test
Requires-Dist: pytest; extra == "test"
Dynamic: license-file
